qilbee_mycelial_network/__init__.py
qilbee_mycelial_network/auth.py
qilbee_mycelial_network/client.py
qilbee_mycelial_network/models.py
qilbee_mycelial_network/retry.py
qilbee_mycelial_network/settings.py
qilbee_mycelial_network-0.1.4.dist-info/licenses/LICENSE
qilbee_mycelial_network-0.1.4.dist-info/METADATA
qilbee_mycelial_network-0.1.4.dist-info/WHEEL
qilbee_mycelial_network-0.1.4.dist-info/top_level.txt
qilbee_mycelial_network-0.1.4.dist-info/RECORD
