Metadata-Version: 2.4
Name: qilbee-mycelial-network
Version: 0.1.4
Summary: Enterprise SaaS SDK for Qilbee Mycelial Network - Adaptive AI Agent Communication
Home-page: https://github.com/qilbee/mycelial-network
Author: AICUBE TECHNOLOGY LLC
Author-email: AICUBE TECHNOLOGY LLC <contact@aicube.ca>, Bruno Ramos <bramos@aicube.ca>
Maintainer-email: AICUBE TECHNOLOGY LLC <contact@aicube.ca>
License-Expression: MIT
Project-URL: Homepage, http://www.qilbee.io
Project-URL: Documentation, http://www.qilbee.io/docs
Project-URL: Repository, https://github.com/qilbee/mycelial-network
Project-URL: Issues, https://github.com/qilbee/mycelial-network/issues
Project-URL: Changelog, https://github.com/qilbee/mycelial-network/releases
Project-URL: Source Code, https://github.com/qilbee/mycelial-network
Keywords: ai,agents,mycelial,network,distributed,ml,machine-learning,artificial-intelligence,multi-agent,communication,embeddings,vector-search,reinforcement-learning,saas,enterprise
Classifier: Development Status :: 3 - Alpha
Classifier: Intended Audience :: Developers
Classifier: Intended Audience :: Science/Research
Classifier: Topic :: Software Development :: Libraries :: Python Modules
Classifier: Topic :: Scientific/Engineering :: Artificial Intelligence
Classifier: Programming Language :: Python :: 3
Classifier: Programming Language :: Python :: 3.9
Classifier: Programming Language :: Python :: 3.10
Classifier: Programming Language :: Python :: 3.11
Classifier: Programming Language :: Python :: 3.12
Classifier: Programming Language :: Python :: 3.13
Classifier: Operating System :: OS Independent
Classifier: Framework :: AsyncIO
Classifier: Typing :: Typed
Requires-Python: >=3.9
License-File: LICENSE
Requires-Dist: httpx>=0.25.0
Requires-Dist: pydantic>=2.0.0
Provides-Extra: dev
Requires-Dist: pytest>=7.0.0; extra == "dev"
Requires-Dist: pytest-asyncio>=0.21.0; extra == "dev"
Requires-Dist: pytest-cov>=4.0.0; extra == "dev"
Requires-Dist: black>=23.0.0; extra == "dev"
Requires-Dist: ruff>=0.1.0; extra == "dev"
Requires-Dist: mypy>=1.0.0; extra == "dev"
Provides-Extra: grpc
Requires-Dist: grpcio>=1.50.0; extra == "grpc"
Requires-Dist: grpcio-tools>=1.50.0; extra == "grpc"
Provides-Extra: quic
Requires-Dist: aioquic>=0.9.0; extra == "quic"
Provides-Extra: telemetry
Requires-Dist: opentelemetry-api>=1.20.0; extra == "telemetry"
Requires-Dist: opentelemetry-sdk>=1.20.0; extra == "telemetry"
Requires-Dist: opentelemetry-instrumentation-httpx>=0.41b0; extra == "telemetry"
Provides-Extra: all
Requires-Dist: grpcio>=1.50.0; extra == "all"
Requires-Dist: grpcio-tools>=1.50.0; extra == "all"
Requires-Dist: aioquic>=0.9.0; extra == "all"
Requires-Dist: opentelemetry-api>=1.20.0; extra == "all"
Requires-Dist: opentelemetry-sdk>=1.20.0; extra == "all"
Requires-Dist: opentelemetry-instrumentation-httpx>=0.41b0; extra == "all"
Dynamic: author
Dynamic: home-page
Dynamic: license-file
Dynamic: requires-python
